# 运行模型：javac、字节码、JVM 与 JIT

C/C++ 的编译链路是单段式的：`gcc`/`clang` 把 `.c` 源码直接编成目标 CPU 架构的机器码，链接后得到一个绑定特定 OS/架构的可执行文件。Java 是**两段式**的：`javac` 先把源码编译成平台无关的中间表示（字节码），再由 JVM 在目标机器上把字节码变成实际执行的指令。本章讲清这条链路的每一环，以及为什么要多插入字节码这一层——这是理解后续内存模型、调用栈、并发一切内容的地基。

## 一、编译与运行的最小流程

Java 程序的最小骨架：一个 **class**，里面一个 `main` 方法，程序从 `main` 开始跑。

```java
// Hello.java
public class Hello {
    public static void main(String[] args) {
        System.out.println("Hello, Java");
    }
}
```

几条直接能上手的规则：

- **文件名必须和 `public class` 的名字完全一致**：这个类叫 `Hello`，文件就必须叫 `Hello.java`。
- **编译**：`javac Hello.java` —— 产出一个 `Hello.class` 文件。
- **运行**：`java Hello` —— 注意是类名 `Hello`，不带 `.class` 后缀，也不是文件名。

```
javac Hello.java
java Hello
```

输出：

```
Hello, Java
```

再写一个带变量和运算的，巩固"编译 → 运行"这套流程：

```java
// Add.java
public class Add {
    public static void main(String[] args) {
        int a = 3;
        int b = 4;
        int sum = a + b;
        System.out.println(sum);
    }
}
```

```
javac Add.java
java Add
```

输出：

```
7
```

`javac` 编译、`java` 运行，IDE 也只是替你自动执行这两步。这两步背后是什么,是本章要拆开讲的内容。

## 二、从源码到字节码：javac 产出什么

```java
// Hello.java
public class Hello {
    public static void main(String[] args) {
        int sum = 0;
        for (int i = 0; i < 10; i++) {
            sum += i;
        }
        System.out.println(sum);
    }
}
```

编译：

```
javac Hello.java     # 产出 Hello.class
```

`javac` 与 `gcc` 的**本质区别**：`gcc` 的输出面向真实 CPU，指令集是 x86-64 / ARM64；`javac` 的输出面向一台假想的**栈式虚拟机**，指令集就是"字节码"（bytecode）。字节码不假设寄存器数量、不假设字长、不假设字节序——它只面向 JVM 规范定义的抽象机器。这就是"一次编写，到处运行"的技术根基：`.class` 文件在 Windows/Linux/macOS、x86/ARM 上是**逐字节相同**的。

`.class` 文件是一个有严格格式的二进制容器（魔数 `0xCAFEBABE` 开头），里面包含：

| 区段 | 内容 | C/C++ 类比 |
|------|------|-----------|
| 常量池 constant pool | 字符串、类名、方法名、字面量的符号引用 | 类似 `.rodata` + 符号表，但更结构化 |
| 字段表 | 类的字段声明 | struct 成员布局信息 |
| 方法表 | 每个方法的字节码 + 元数据 | 函数体，但带完整类型签名 |
| 属性表 | 行号表、局部变量表、注解等 | 调试信息（类似 DWARF），但内置 |

**为什么要多插入字节码这一层，而不是像 `gcc` 一样直接编译到机器码**：这是"可移植性"与"极致性能"之间一次明确的取舍。直接编译到机器码（AOT，Ahead-Of-Time）能让编译器在编译期看到完整的目标 CPU 特性，做深入的静态优化，程序启动即以峰值速度运行，但产物与目标 CPU 架构、操作系统、ABI 强绑定——挪到另一种 CPU 就要重新编译，这是 C/C++ "一次编写，各平台分别编译"模型的代价。Java 把"翻译成具体机器指令"这一步推迟到运行时，编译器只需要面向一台抽象的栈式虚拟机，产出的 `.class` 文件在任何装了 JVM 的机器上逐字节相同，换来"一次编写，到处运行"；代价是运行时必须多做一轮翻译（解释或 JIT 编译），程序启动阶段无法立刻达到原生代码的速度。第三节的 JIT 和第五节的 GraalVM AOT 会看到这套取舍具体如何被弥补或反向选择。

关键点：**`.class` 保留了完整的类型与符号信息**。C 程序 strip 之后几乎只剩机器码，符号丢失；而 `.class` 天然携带类名、方法签名、字段类型——这是反射、动态加载、运行时类型检查得以存在的物质基础。

下面这段代码就靠这些留存的信息，在**运行时**读出方法的精确签名——这在 `strip` 过的 C 二进制上是做不到的：

```java
import java.lang.reflect.Method;

Class<?> c = java.util.ArrayList.class;
System.out.println("class = " + c.getName());
Method m = c.getMethod("add", Object.class);
System.out.println("method = " + m.getName());
System.out.println("returns = " + m.getReturnType().getName());
System.out.println("params = " + m.getParameterCount());
// 输出：
// class = java.util.ArrayList
// method = add
// returns = boolean
// params = 1
```

### 用 javap 看字节码

`javap` 是 JDK 自带的反汇编器，相当于 Java 世界的 `objdump -d`：

```
javap -c Hello.class
```

`main` 方法的字节码大致如下（注释我加的）：

```
0:  iconst_0        // 把常量 0 压入操作数栈
1:  istore_1        // 弹出栈顶存入局部变量表 slot 1（即 sum）
2:  iconst_0        // 常量 0 入栈
3:  istore_2        // 存入 slot 2（即 i）
4:  iload_2         // 加载 i 入栈
5:  bipush 10       // 常量 10 入栈
7:  if_icmpge 20    // 若 i >= 10 跳到偏移 20（退出循环）
10: iload_1         // 加载 sum
11: iload_2         // 加载 i
12: iadd            // 栈顶两值相加，结果留在栈上
13: istore_1        // 存回 sum
14: iinc 2, 1       // 直接对 slot 2（i）自增 1，不经过操作数栈
17: goto 4          // 回到循环判断
20: getstatic ...   // 取 System.out
23: iload_1
24: invokevirtual println
27: return
```

注意 `iconst`/`istore`/`iload`/`iadd` 这些指令**没有寄存器操作数**。JVM 是**栈式机器**：运算的输入输出都在"操作数栈"上流转，而不是像 x86 那样 `add eax, ebx` 指名寄存器。`i` 前缀表示操作 int 类型，还有 `l`(long)、`f`(float)、`d`(double)、`a`(引用 address)。`iinc` 是少见的能直接改局部变量表的指令。

> 每个方法在字节码里都声明了它需要多大的操作数栈（`stack=`）和多少个局部变量 slot（`locals=`）。这些是编译期就算好的固定值，JVM 据此分配栈帧——见[「函数与调用栈」](06-函数与调用栈.md)。

## 三、类加载：把 .class 装进 JVM

C 程序启动时，加载器（loader）把 ELF 段映射进内存，重定位、绑定动态库符号，一次性搞定。Java 的类加载是**惰性的、按需的、运行期的**，分三个阶段。

**为什么类加载要设计成懒加载**：一个典型 Java 程序在编译期依赖成百上千个类（JDK 核心类库 + 第三方库），如果启动时像 C 静态链接那样把全部依赖一次性加载解析完毕，启动时间会随依赖图规模线性增长，而其中大多数类在这次运行里根本用不到（一个分支从未走到的异常处理类、一个从未触发的功能模块）。懒加载把加载/链接/初始化的开销分摊到"第一次真正用到该类"的那一刻，未被触碰的类完全零开销，这是"启动快"这一目标下的直接工程选择。它还有一个次生好处：类可以来自还不存在的地方（网络、动态生成的字节码、插件在运行时才提供的实现），只要在真正使用前能找到字节流即可——这在"必须在链接期见到全部符号"的静态链接模型下是做不到的。

### 1. 加载 Loading
根据类的全限定名找到 `.class` 字节流（从文件系统、jar、网络、甚至运行时生成），解析成方法区/元空间里的一个内部数据结构，并在堆上创建一个代表该类的 `java.lang.Class` 对象。这一步类似 `dlopen` 打开一个库，但粒度是单个类。

### 2. 链接 Linking（三小步）
- **验证 Verification**：检查字节码是否合法、类型是否安全、栈是否会溢出/下溢。C/C++ 没有对应物——它信任编译器产出的机器码；JVM 因为可能加载来路不明的字节码，必须做这层安全校验。
- **准备 Preparation**：为静态字段分配空间并置**零值**（int→0，引用→null）。注意此时不执行用户赋值。
- **解析 Resolution**：把常量池里的**符号引用**（"类 A 的方法 foo"）替换为**直接引用**（内存地址/偏移）。这相当于 C 的链接期符号解析，但发生在运行时，且可以延迟到第一次使用时才做。

### 3. 初始化 Initialization
执行静态初始化块和静态字段的赋值（即 `<clinit>` 方法）。触发时机：首次 `new`、访问静态字段/方法、反射等。JVM 保证 `<clinit>` 在多线程下**只执行一次**（带锁），这也是"静态单例 + 类加载"惯用法线程安全的原因。

下面这段代码验证了"惰性 + 只一次"：`Config` 的静态初始化直到**第一次主动使用**才发生，且再次访问不会重复执行：

```java
static class Config {
    static { System.out.println("  [Config <clinit> runs]"); }
    static final int READY = compute();
    static int compute() { System.out.println("  [compute() runs]"); return 42; }
}
public static void main(String[] a) {
    System.out.println("main start");
    System.out.println("before touching Config");
    int v = Config.READY;   // 第一次主动使用 -> 触发 <clinit>
    System.out.println("Config.READY = " + v);
    int v2 = Config.READY;  // 再次访问 -> <clinit> 不会重复执行
    System.out.println("Config.READY = " + v2);
}
// 输出：
// main start
// before touching Config
//   [Config <clinit> runs]
//   [compute() runs]
// Config.READY = 42
// Config.READY = 42
```

注意 `[Config <clinit> runs]` 出现在 `before touching Config` **之后**——类加载确实推迟到了用到它的那一刻。

### 双亲委派模型 Parent Delegation

JVM 里有多个类加载器，形成层级：

```
        Bootstrap ClassLoader   (C++ 实现，加载 java.* 核心类)
              ▲  委派
        Platform ClassLoader    (JDK 平台模块)
              ▲  委派
        Application ClassLoader (你的 classpath)
              ▲  委派
        自定义 ClassLoader
```

加载一个类时，子加载器**先向上委派**给父加载器尝试，父加载不了才自己加载。好处：核心类（如 `java.lang.String`）永远由 Bootstrap 加载，你没法用一个伪造的 `java.lang.String` 顶替系统类——这是一种安全与一致性保证。C/C++ 里若两个 `.so` 各自带同名符号，行为取决于链接顺序，容易出问题；双亲委派从机制上避免了核心类被"劫持"。

## 四、执行：解释 + JIT 混合模式

拿到字节码后，JVM 怎么执行？两种手段并用（HotSpot 的默认"混合模式"）：

### 解释执行
JVM 内置一个字节码解释器，逐条读取字节码、查表、执行对应的 C++ 逻辑。启动快（不用等编译），但每条指令都有解释开销，比原生机器码慢一到两个数量级。

### 热点探测 + JIT 编译
HotSpot 这个名字就来自它的策略：**探测热点代码**（Hot Spot）。JVM 为每个方法维护计数器（方法调用次数 + 循环回边次数），一旦超过阈值，就认定它"热"，交给 **JIT（Just-In-Time）编译器**把这段字节码**在运行时**编译成本地机器码，之后直接执行机器码。

HotSpot 有两个 JIT 编译器（分层编译 Tiered Compilation 会协同使用）：

| 编译器 | 定位 | 特点 |
|--------|------|------|
| C1（Client） | 快速编译 | 优化少，编译快，先顶上 |
| C2（Server） | 深度优化 | 激进优化，编译慢，用于最热的代码 |

典型路径：解释执行 → C1 编译（带性能计数）→ C2 重编译最热部分。

**为什么需要 JIT，而不是纯解释或纯 AOT 二选一**：三种方案各自卡在一个极端。纯解释器启动零延迟（不用等编译），但每条字节码都要经过"取指-查表-分派"的开销，长期运行的代码也一直慢；纯 AOT（如 `gcc`）能提前做深度优化，但编译期看不到运行时才知道的信息（这次运行里某个虚方法调用点实际上只被一个实现类命中、某个循环实际迭代了几十亿次值得激进展开），只能基于静态假设做保守优化。JIT 把两者的优点拼在一起：先用解释执行（或最快的 C1）立刻跑起来，避免启动等待；同时用计数器持续观察运行时行为,一旦某段代码被证实"热"，才投入编译期成本更高、优化更激进的 C2,用实际观测到的分支概率、类型信息做静态编译器不敢做的**投机优化**。**分层编译（Tiered Compilation）**正是"启动延迟"与"峰值吞吐"这对矛盾的调和方案：C1 编译快、优化保守，负责让代码尽早摆脱解释执行的慢速；C2 编译慢、优化激进，只对少数真正的热点方法投入，避免把编译时间浪费在只跑一次的代码上。赌错的投机优化可以**去优化（deoptimization）**退回解释执行重新收集信息，这是"运行时信息可能过时或不全"这一代价的兜底机制。

**这就是 Java "越跑越快"、且有时能逼近甚至局部超过 C 的原因**：JIT 掌握**运行时信息**——实际走哪个分支、某个虚方法实际只调用了一个实现类、某个循环边界是多少。它能据此做静态编译器做不到的**投机优化**（speculative optimization），赌错了再"去优化"（deoptimization）退回解释执行。而 `gcc` 编译时对运行时一无所知，只能保守。

### 几个关键 JIT 优化（对内存行为影响很大）

- **方法内联 Inlining**：把被调方法体直接嵌入调用处，消除调用开销，还打开了后续优化的视野。等价于 C 的 `inline`，但 JIT 是**运行时**基于热度自动决定的。
- **逃逸分析 Escape Analysis**：分析一个对象的引用是否"逃逸"出当前方法（是否被返回、被存入堆上其它对象、被其它线程看到）。若**不逃逸**，JVM 可以做：
  - **标量替换（Scalar Replacement）**：把本该在堆上 new 的对象**拆散**成它的各个字段，当作普通局部变量直接放进**栈帧 slot 甚至寄存器**。注意这不是"把整个对象搬到栈上"，而是对象作为一个整体**根本不再存在**——因此既没有堆分配、也无需 GC 回收。（HotSpot 并没有真正的"整对象栈上分配"，能省掉堆分配的机制就是标量替换。）

这一点对你理解 Java 内存很重要：Java 语言层面"对象一律在堆上"，但 HotSpot 实现层面，逃逸分析可能让短命的、不逃逸的对象根本不进堆。这弥合了 Java 与 C（栈上放 struct）的部分性能差距。详见[「变量与内存模型」](03-变量与内存模型.md)。

## 五、运行时内存区域

一个运行中的 JVM 把内存划成几块（JVM 规范定义，HotSpot 实现）：

```
┌───────────────────────────────────────────────────────┐
│                         JVM 进程                         │
│                                                         │
│  所有线程共享 ↓                                          │
│  ┌─────────────────────┐   ┌───────────────────────┐   │
│  │        堆 Heap        │   │  方法区 / 元空间         │   │
│  │  所有对象、数组       │   │  类元数据、方法字节码    │   │
│  │  GC 主战场            │   │  运行时常量池           │   │
│  │  (new 出来的都在这)   │   │  (元空间在本地内存)      │   │
│  └─────────────────────┘   └───────────────────────┘   │
│                                                         │
│  每个线程私有 ↓                                          │
│  ┌───────────┐ ┌───────────┐ ┌──────────┐ ┌──────────┐ │
│  │ JVM 栈     │ │ PC 寄存器  │ │本地方法栈 │ │ ...      │ │
│  │ 一堆栈帧   │ │ 当前指令   │ │JNI 用     │ │每线程一份 │ │
│  └───────────┘ └───────────┘ └──────────┘ └──────────┘ │
└───────────────────────────────────────────────────────┘
```

| 区域 | 谁的 | 存什么 | C/C++ 类比 |
|------|------|--------|-----------|
| 堆 Heap | 共享 | 所有对象、数组实例 | malloc 的堆，但由 GC 自动回收 |
| 方法区/元空间 Metaspace | 共享 | 类结构、方法字节码、运行时常量池、静态字段的**元信息**（字段的**值**存放在堆上的 `Class` 镜像对象里，不在元空间） | 代码段 + 只读数据段（但可运行时增长） |
| JVM 栈 | 每线程 | 栈帧（局部变量表、操作数栈） | 线程调用栈，逻辑一致 |
| PC 寄存器 | 每线程 | 当前执行到的字节码地址 | 程序计数器 PC/RIP |
| 本地方法栈 | 每线程 | 执行 native（JNI）方法时的栈 | C 侧的原生栈 |

几点与 C 的对照：
- **元空间在本地内存（native memory）**，不在 GC 堆里（这是 JDK8 起的设计，取代了旧的"永久代 PermGen"）。
- **堆的回收是自动的**：没有 `free`/`delete`，GC 判定不可达就回收。你几乎从不手动管理堆生命周期——这是与 C 最大的心智差异，也是[「错误处理与资源管理」](09-错误处理与资源管理.md)里 `try-with-resources` 只针对"非内存资源"（文件/socket）的原因：内存交给 GC，句柄仍需显式关。
- **栈的语义几乎和 C 一样**：每次方法调用压一个栈帧，返回时弹出；栈太深触发 `StackOverflowError`（对应 C 的栈溢出，但 JVM 会抛异常而非直接段错误）。

## 六、AOT：GraalVM native-image

Java 也能像 C 一样**提前编译（Ahead-Of-Time）**成原生可执行文件。**GraalVM 的 `native-image`** 在构建期做闭包分析，把用到的类、方法、乃至一个精简的运行时（含 GC）静态编译打包成一个独立可执行文件：

```
native-image Hello        # 产出一个原生可执行文件 hello
./hello                   # 无需 JVM，毫秒级启动
```

代价与取舍：
- **优点**：启动极快、内存占用小、无需分发 JVM——适合 CLI 工具、Serverless/函数计算冷启动。这时它和 C 的分发模型很像：一个原生二进制。
- **代价**：构建期必须知道全部会用到的类，因此**反射、动态代理、运行时生成类**需要额外配置；失去了 JIT 的运行时投机优化，峰值吞吐**可能不如**长时间预热后的 C2。

所以对照记忆：
- `javac` → 字节码，跨平台，靠 JVM + JIT 运行时优化（长跑服务的主流）。
- `native-image` → 原生码，绑定平台，构建期定死（快启动短命进程的选择）。
- `gcc/clang` → 原生码，绑定平台，编译期定死（C/C++ 的唯一路径）。

## 小结

- **流程**：`javac 文件名.java` 编译（类名须与文件名一致）→ `java 类名`（不带后缀）运行；IDE 只是自动执行这两步。
- `javac` 产出**平台无关字节码**而非机器码，代价是运行时需要 JVM 这台栈式虚拟机再翻译一遍，换来的是同一份 `.class` 到处运行；这是可移植性与 AOT 峰值性能之间的取舍。
- 类加载是**运行时、惰性、分层（双亲委派）**的——懒加载把开销分摊到真正用到某个类的那一刻，避免为用不到的类付出启动成本；双亲委派保证核心类不会被伪造版本顶替。
- HotSpot **先解释、探测热点后 JIT**（C1 快编译顶上、C2 深度优化最热代码），分层编译正是"启动延迟"与"峰值吞吐"这对矛盾的调和；逃逸分析能对不逃逸对象做**标量替换**（拆成标量放栈帧/寄存器，而非整体栈上分配）。
- 运行时内存分**共享的堆/元空间**与**每线程的 JVM 栈/PC/本地栈**；堆由 GC 自动回收。
- 需要 C 式的快启动原生二进制时，用 GraalVM `native-image` 做 AOT，代价是牺牲运行时动态性与峰值优化。

---
[← 上一章：目录](index.md) · [返回目录](index.md) · [下一章：基础语法](02-基础语法.md) →
